<?xml version="1.0" encoding="UTF-8" standalone="yes"?> 
<addons>
<?xml version="1.0" encoding="UTF-8" standalone="yes"?>
<addon id="plugin.program.beta.wizard" name="Wardoctors Beta Wizard" version="1.0.6" provider-name="Wardoctor">
  <requires>
    <import addon="xbmc.python" version="2.1.0"/>
  </requires>
  <extension point="xbmc.python.pluginsource" library="default.py">
    <provides>executable</provides>
  </extension>
  <extension point="xbmc.service" library="startup.py" start="startup" />
  <extension point="xbmc.addon.metadata">
    <summary lang="en">Wardoctors Beta Wizard</summary>
    <description lang="en">Wardoctors Beta Test Wizard.</description>
    <platform>all</platform>
  </extension>
</addon>
<?xml version="1.0" encoding="UTF-8" standalone="yes"?>
<addon id="repository.wardoctor" name="Wardoctors Repo" version="1.0.1" provider-name="Wardoctor">
	<extension point="xbmc.addon.repository" name="Wardoctors Repository">
		<info compressed="false">https://raw.githubusercontent.com/thewardoctor/Wardoctors-repo/master/addons.xml</info>
		<checksum>https://raw.githubusercontent.com/thewardoctor/Wardoctors-repo/master/addons.xml.md5</checksum>
		<datadir zip="true">https://raw.githubusercontent.com/thewardoctor/Wardoctors-repo/master/</datadir>
	</extension>
	<extension point="xbmc.addon.metadata">
		<summary>Wardoctors repo for Kodi Stuff, don't like it? Go away, problem solved.</summary>
		<description></description>
		<disclaimer></disclaimer>
		<platform>all</platform>
	</extension>
</addon>
<?xml version="1.0" encoding="UTF-8" standalone="yes"?>
<addon id="repository.Tardisrepo" name="Tardis Repository" version="1.5" provider-name="The Tenth Doctor">
	<extension point="xbmc.addon.repository" name="Tardis Repository">
		<info compressed="false">https://raw.githubusercontent.com/tardisbuilds/Tardisbuilds-Repository/master/addons.xml</info>
		<checksum>https://raw.githubusercontent.com/tardisbuilds/Tardisbuilds-Repository/master/addons.xml.md5</checksum>
		<datadir zip="true">https://raw.githubusercontent.com/tardisbuilds/Tardisbuilds-Repository/master</datadir>
	</extension>
	<extension point="xbmc.addon.metadata">
		<summary></summary>
		<description></description>
		<platform>all</platform>
	</extension>
</addon>
<?xml version="1.0" encoding="UTF-8" standalone="yes"?>
<addon id="repository.elysium" version="2017.10.14" name="Elysium repository" provider-name="Elysium">
	<requires>
		<import addon="xbmc.python" version="2.19.0" />
	</requires>
	<extension point="xbmc.addon.repository" name="Elysium repository">
		<dir minversion="14.0.0">
			<info compressed="false">https://raw.githubusercontent.com/noobsandnerds/modules4all/master/zips/addons.xml</info>
			<checksum>https://raw.githubusercontent.com/noobsandnerds/modules4all/master/zips/addons.xml.md5</checksum>
			<datadir zip="true">https://raw.githubusercontent.com/noobsandnerds/modules4all/master/zips/</datadir>
		</dir>
		<dir minversion="14.0.0">
			<info compressed="false">https://github.com/OpenELEQ/repository.elysium/raw/master/elysium.xml</info>
			<checksum>https://github.com/OpenELEQ/repository.elysium/raw/master/elysium.xml.md5</checksum>
			<datadir zip="true">https://raw.github.com/OpenELEQ/repository.elysium/master/</datadir>
		</dir>
	</extension>
	<extension point="xbmc.addon.metadata">
		<summary lang="en">Elysium repository</summary>
		<description lang="en">This repository contains Elysium and required dependencies.</description>
		<disclaimer lang="en">The author does not host or share any content, nor is he affiliated with any of the content providers.</disclaimer>
		<platform>all</platform>
		<news>Added module4all repodir</news>
		<assets>
			<icon>icon.png</icon>
			<fanart>fanart.jpg</fanart>
		</assets>
	</extension>
</addon>
<?xml version="1.0" encoding="UTF-8" standalone="yes"?>
<addon id="repository.Cypherslocker" name="[COLOR cornflowerblue]Cyphers locker[/COLOR]" version="1.0.2" provider-name="Project Cypher">
	<extension point="xbmc.addon.repository" name="TheMegaRepo">
		<info compressed="false">https://github.com/CypherMediaGIT/CypherRepo/raw/master/cypherrepo/plugins/addons.xml</info>
		<checksum>https://github.com/CypherMediaGIT/CypherRepo/raw/master/cypherrepo/plugins/addons.xml.md5</checksum>
		<datadir zip="true">https://github.com/CypherMediaGIT/CypherRepo/raw/master/cypherrepo/plugins</datadir>
	</extension>
	<extension point="xbmc.addon.metadata">
		<summary>Cypers Locker Repo - Home to Project Cypher</summary>
		<description>Cypers Locker Repo - Home to Project Cypher.</description>
		<platform>all</platform>
	</extension>
</addon>
<?xml version="1.0" encoding="UTF-8" standalone="yes"?>
<addon id="repository.jesusboxtv" name="Jesusbox Repository" version="1.0.3" provider-name="Playonmonkey">
	<extension point="xbmc.addon.repository" name="Jesusbox Repository">
		<info compressed="false">https://raw.githubusercontent.com/jesusboxrepo/repository/master/addons.xml</info>
		<checksum>https://raw.githubusercontent.com/jesusboxrepo/repository/master/addons.xml.md5</checksum>
		<datadir zip="true">https://raw.githubusercontent.com/jesusboxrepo/repository/master/</datadir>
	</extension>
	<extension point="xbmc.addon.metadata">
		<summary>Welcome to the Jesusbox Repository where you will find all Jesusbox produced Addon-ons and wizards</summary>
		<description>The Best Media Center Box Available</description>
		<platform>all</platform>
	</extension>
</addon>
<?xml version="1.0" encoding="UTF-8" standalone="yes"?>
<addon id="repository.noobsandnerds" name="noobsandnerds Repository" version="2.3.2" provider-name="noobsandnerds">
        <extension point="xbmc.addon.repository" name="noobsandnerds Repository">
                <dir>
                        <info compressed="false">https://raw.githubusercontent.com/noobsandnerds/modules4all/master/zips/addons.xml</info>
                        <checksum>https://raw.githubusercontent.com/noobsandnerds/modules4all/master/zips/addons.xml.md5</checksum>
                        <datadir zip="true">https://raw.githubusercontent.com/noobsandnerds/modules4all/master/zips/</datadir>
                </dir>
                <dir>
                        <info compressed="false">https://raw.githubusercontent.com/alfreddempsey3/repository.rage/master/zips/addons.xml</info>
                        <checksum>https://raw.githubusercontent.com/alfreddempsey3/repository.rage/master/zips/addons.xml.md5</checksum>
                        <datadir zip="true">https://raw.githubusercontent.com/alfreddempsey3/repository.rage/master/zips/</datadir>
                </dir>
                <dir>
                        <info compressed="false">https://raw.githubusercontent.com/bromerzz/repository.bromcy/master/zips/addons.xml</info>
                        <checksum>https://raw.githubusercontent.com/bromerzz/repository.bromcy/master/zips/addons.xml.md5</checksum>
                        <datadir zip="true">https://raw.githubusercontent.com/bromerzz/repository.bromcy/master/zips/</datadir>
                        </dir>
                <dir>
                        <info compressed="false">https://github.com/OpenELEQ/repository.elysium/raw/master/elysium.xml</info>
                        <checksum>https://github.com/OpenELEQ/repository.elysium/raw/master/elysium.xml.md5</checksum>
                        <datadir zip="true">https://raw.github.com/OpenELEQ/repository.elysium/master/</datadir>
                </dir>
                        <dir>
                        <info compressed="true">https://raw.githubusercontent.com/catchup4kodi/catchup4kodi/master/zips/addons.xml</info>
                        <checksum>https://raw.githubusercontent.com/catchup4kodi/catchup4kodi/master/zips/addons.xml.md5</checksum>
                        <datadir zip="true">https://raw.githubusercontent.com/catchup4kodi/catchup4kodi/master/zips/</datadir>
                </dir>
                <dir>
                        <info compressed="false">https://raw.githubusercontent.com/midraal/repository.midraal/master/zips/addons.xml</info>
                        <checksum>https://raw.githubusercontent.com/midraal/repository.midraal/master/zips/addons.xml.md5</checksum>
                        <datadir zip="true">https://raw.github.com/midraal/repository.midraal/master/zips/</datadir>
                </dir>
                <dir minversion="14.0.0">
                        <info compressed="false">https://github.com/OpenELEQ/repository.q/raw/master/openeleq-addons.xml</info>
                        <checksum>https://github.com/OpenELEQ/repository.q/raw/master/openeleq-addons.xml.md5</checksum>
                        <datadir zip="true">https://raw.github.com/OpenELEQ/repository.q/master/zips/</datadir>
                </dir>
                <dir minversion="16.0.0">
                        <info compressed="false">https://github.com/OpenELEQ/repository.q.jarvis/raw/master/openeleq-addons.xml</info>
                        <checksum>https://github.com/OpenELEQ/repository.q.jarvis/raw/master/openeleq-addons.xml.md5</checksum>
                        <datadir zip="true">https://raw.github.com/OpenELEQ/repository.q.jarvis/master/zips/</datadir>
                </dir>
                <dir minversion="16.9.9">
                        <info compressed="false">https://github.com/OpenELEQ/repository.q.krypton/raw/master/openeleq-addons.xml</info>
                        <checksum>https://github.com/OpenELEQ/repository.q.krypton/raw/master/openeleq-addons.xml.md5</checksum>
                        <datadir zip="true">https://raw.github.com/OpenELEQ/repository.q.krypton/master/zips/</datadir>
                </dir>
                <info compressed="false">https://raw.githubusercontent.com/noobsandnerds/noobsandnerds/master/zips/addons.xml</info>
                <checksum>https://raw.githubusercontent.com/noobsandnerds/noobsandnerds/master/zips/addons.xml.md5</checksum>
                <datadir zip="true">https://raw.githubusercontent.com/noobsandnerds/noobsandnerds/master/zips/</datadir>
        </extension>
        <extension point="xbmc.addon.metadata">
                <summary>Home of The Community Portal</summary>
                <description>Visit www.noobsandnerds.com and become a part of our great family, you get to choose what The Community Portal holds!</description>
                <platform>all</platform>
        </extension>
</addon>
<?xml version="1.0" encoding="UTF-8"?>
    <addon id="repository.SpinzTV" name="SpinzTV" version="0.1.4" provider-name="SpinzTV">
        <requires>
            <import addon="xbmc.addon" version="12.0.0"/>
        </requires>
        <extension point="xbmc.addon.repository" name="SpinzTV">
		<dir>
			<info compressed="false">https://raw.githubusercontent.com/noobsandnerds/modules4all/master/zips/addons.xml</info>
			<checksum>https://raw.githubusercontent.com/noobsandnerds/modules4all/master/zips/addons.xml.md5</checksum>
			<datadir zip="true">https://raw.githubusercontent.com/noobsandnerds/modules4all/master/zips/</datadir>
		</dir>
            <info compressed="false">http://raw.github.com/spinztv/pro/master//_repo/addons.xml</info>
            <checksum>http://raw.github.com/spinztv/pro/master//_repo/addons.xml.md5</checksum>
            <datadir zip="true">http://raw.github.com/spinztv/pro/master//_repo/</datadir>
            <hashes>false</hashes>
        </extension>
        <extension point="xbmc.addon.metadata">
            <summary>SpinzTV</summary>
            <description>SpinzTV - General Disclaimer: By downloading or using you are agreeing that the author takes no resposibility for the content or reliability of any of the addons included.  The author does not host, distribute or have any control over any of the content that may be provided by any addon. It is the users responsibility to ensure the legality of use within their country.</description>
            <platform>all</platform>
    </extension>
</addon>
<?xml version="1.0" encoding="UTF-8" standalone="yes"?>
<addon 	id="repository.streamhub" 
		name="[COLOR red]StreamHub Repository[/COLOR]" 
		version="1.2" 
		provider-name="sClarke">
	<extension point="xbmc.addon.repository" name="[COLOR red]StreamHub Repository[/COLOR]">
		<info compressed="false">https://raw.githubusercontent.com/sClarkeIsBack/StreamHub/master/Repo_Files/addons.xml</info>
		<checksum>https://raw.githubusercontent.com/sClarkeIsBack/StreamHub/master/Repo_Files/addons.xml.md5</checksum>
		<datadir zip="true">https://raw.githubusercontent.com/sClarkeIsBack/StreamHub/master/Repo_Files/Zips</datadir>
	</extension>
	<extension point="xbmc.addon.metadata">
		<summary>StreamHub</summary>
		<description>StreamHub Repository - Bringing You StreamHub</description>
		<platform>all</platform>
	</extension>
</addon>
<?xml version="1.0" encoding="UTF-8" standalone="yes"?>
<addon id="repository.zt" name="[COLORred]Z[/COLOR]ero [COLORwhite]T[/COLOR]olerance Repository" version="1.0.1" provider-name="Team ZT">
		<extension point="xbmc.addon.repository" name="Bla Bla Repository">
			<info compressed="false">http://zt.r3trozt.tk/repo/addons.xml</info>
			<checksum>http://zt.r3trozt.tk/repo/addonsmd5.txt</checksum>
			<datadir zip="true">http://zt.r3trozt.tk/repo/addons/</datadir>
		</extension>
		<extension point="xbmc.addon.metadata">
			<summary></summary>
			<description></description>
			<platform>all</platform>
		</extension>
</addon>
<?xml version="1.0" encoding="UTF-8" standalone="yes"?>
<addon id="repository.adulthideout" name="AdultHideout REPO" version="1.0.1" provider-name="Vashiel">
	<extension point="xbmc.addon.repository" name="AdultHideout Addon Repository">
		<info compressed="false">https://github.com/Vashiel/repository.adulthideout/raw/master/addons.xml</info>
		<checksum>https://github.com/Vashiel/repository.adulthideout/raw/master/addons.xml.md5</checksum>
		<datadir zip="true">https://github.com/Vashiel/repository.adulthideout/raw/master/zips</datadir>
	</extension>
	<extension point="xbmc.addon.metadata">
		<summary>AdultHideout Addon Repository</summary>
		<description>First Try for a Adult Kodi Addon</description>
		<platform>all</platform>
	</extension>
</addon>
<?xml version="1.0" encoding="UTF-8" standalone="yes"?>
<addon id="repository.BludhavenGrayson" name="BludhavenGrayson Add-ons" version="1.0.0" provider-name="BludhavenGrayson">
	<extension point="xbmc.addon.repository" name="BludhavenGrayson Repository">
		<info compressed="false">http://raw.github.com/BludhavenGrayson/repository.BludhavenGrayson/master/addons.xml</info>
		<checksum>http://raw.github.com/BludhavenGrayson/repository.BludhavenGrayson/master/addons.xml.md5</checksum>
		<datadir zip="true">http://raw.github.com/BludhavenGrayson/repository.BludhavenGrayson/master/zips</datadir>
	</extension>
	<extension point="xbmc.addon.metadata">
		<summary>BludhavenGrayson's Add-ons</summary>
		<description>Download and install add-ons from BludhavenGrayson's Repository.</description>
		<platform>all</platform>
	</extension>
</addon>
<?xml version="1.0" encoding="UTF-8" standalone="yes"?>
<addon id="repository.eracknaphobia" name="eracknaphobia's Repo" version="1.0.0" provider-name="eracknaphobia">
	<extension point="xbmc.addon.repository" name="eracknaphobia's Repo">
		<info compressed="false">https://github.com/eracknaphobia/repo.eracknaphobia/raw/master/addons.xml</info>
		<checksum>https://github.com/eracknaphobia/repo.eracknaphobia/raw/master/addons.xml.md5</checksum>
		<datadir zip="true">https://github.com/eracknaphobia/repo.eracknaphobia/raw/master/addons/</datadir>
	</extension>
	<extension point="xbmc.addon.metadata">
		<summary>eracknaphobia's Repo</summary>
		<description>eracknaphobia's Repo</description>
		<platform>all</platform>
	</extension>
</addon>
<?xml version="1.0" encoding="UTF-8"?>
<addon
  id="plugin.audio.listenliveeu"
  version="1.2.0"
  name="ListenLiveEU"
  provider-name="bootsy, xycl">
  <requires>
   <import addon="xbmc.python" version="2.14.0"/>
   <import addon="script.module.requests" version="2.9.1"/>
  </requires>
  <extension
    point="xbmc.python.pluginsource"
    library="default.py">
   <provides>audio</provides>
  </extension>
  <extension point="xbmc.addon.metadata">
    <summary lang="da">Europæiske radiostationer, som streamer live på nettet</summary>
    <summary lang="de">Europäische Radiostationen, die live im Internet streamen</summary>
    <summary lang="el">Ευρωπαϊκοί ραδιοφωνικοί σταθμοί που εκπέμπουν ζωντανά στο διαδίκτυο</summary>
    <summary lang="en">European radio stations streaming live on the internet</summary>
    <summary lang="hu">Európai internetes rádiók</summary>
    <summary lang="it">Le stazioni radio Europee in streaming dal vivo su internet</summary>
    <summary lang="nl">Internet live streams van Europese radio stations</summary>
    <summary lang="pl">Europejskie stacje radiowe na żywo w internecie</summary>
    <summary lang="pt">Estações de rádio europeias com transmissão ao vivo na internet</summary>
    <summary lang="pt_BR">Estações de rádio europeias ao vivo por transmissão online</summary>
    <summary lang="sk">Európske rádio stanice naživo stramujúce na internete</summary>
    <summary lang="sv">Europeiska radiostationer som sänder direkt över internet</summary>
    <description lang="da">Velkommen til listenlive.eu, en webradio-oversigt med over 4000 radiostationer fra overalt i Europe, som streamer live på nettet.</description>
    <description lang="de">Listenlive.eu ist ein Web-Radio Aggregator mit mehr als 4000 Radiostationen aus Europa.</description>
    <description lang="el">Καλώς ήρθατε στο listenlive.eu, ένα ευρετήριο διαδικτυακών ραδιοφωνικών σταθμών με περισσότερους από 4000 σταθμούς που εκπέμπουν ζωντανά στο διαδίκτυο σε όλη την Ευρώπη.</description>
    <description lang="en">Welcome to listenlive.eu, a web radio directory showcasing over 4000 radio stations from across Europe streaming live on the internet.</description>
    <description lang="hu">A listenlive.eu több mint 4000 élo rádióadást tartalmaz Európából, melyeket az interneten keresztül érhetsz el.</description>
    <description lang="it">Benvenuto a listenlive.eu una web radio che mostra più di 4000 radio stazioni provenienti da tutta Europa in diretta streaming  su internet.</description>
    <description lang="nl">Welkom bij listenlive.eu, een web radio directory met meer dan 4000 radio stations uit heel europa welke live streamen op het internet.</description>
    <description lang="pl">Witamy w listenlive.eu, katalogu ponad 4000 stacji radiowych z całej Europy nadających na żywo w internecie.</description>
    <description lang="pt">Benvindo a listenlive.eu, um directório de rádios web que oferece mais de 4000 estações de rádio de toda a Europa com transmissão ao vivo na internet.</description>
    <description lang="pt_BR">Bem-vindo à listenlive.eu, um diretório de rádio na web que contém mais de 4000 estações de rádio de toda a Europa ao vivo pela internet.</description>
    <description lang="sk">Vitajte na listenlive.eu, web stránke, ktorá prezentuje vyše 4000 rádio staníc z celej Európy streamujúcich naživo na internete.</description>
    <description lang="sv">Välkommen till listenlive.eu, en webbradiokatalog med över 4000 radiostationer från över hela Europa som sänder direkt över internet.</description>
    <platform>all</platform>
    <language></language>
  </extension>
</addon>
<?xml version="1.0" encoding="UTF-8" standalone="yes"?>
<addon id="plugin.audio.mp3streams" name="MP3 Streams" version="2017.11.25" provider-name="qahanik, kinkin, art by Marquerite">
    <requires>
        <import addon="xbmc.python" version="2.1.0"/>
        <import addon="script.module.t0mm0.common" version="1.1.0"/>
        <import addon="script.module.mutagen"/>
        <import addon="script.module.requests" version="1.1.0"/>
    </requires>
    <extension point="xbmc.python.pluginsource" library="default.py">
        <provides>audio</provides>
    </extension>
    <extension point="xbmc.service" library="playerMP3.py" start="startup" />
    <extension point="xbmc.addon.metadata">
        <platform>all</platform>
        <summary>A music streaming collection</summary>
        <description>Browse, stream or download your favourite songs and albums</description>
        <news>fixed by qahanik (thank you very much!) / changed versioning to date-format / fixed album downloading / minor cosmetic cleanups</news>
        <assets>
            <icon>icon.png</icon>
            <fanart>fanart.jpg</fanart>
        </assets>
    </extension>
</addon>
<?xml version="1.0" encoding="UTF-8" standalone="yes"?>
<addon id="plugin.audio.musicbox" name="Music Box" version="0.2.1" provider-name="techdealer">
  <requires>
    <import addon="xbmc.python" version="2.20.0"/>
    <import addon="script.module.simple.downloader" version="1.9.4"/>
    <import addon="plugin.video.youtube" version="2.9.2"/>
    <import addon="script.module.mutagen"/>
    <import addon="script.module.requests" version="2.3.0"/>
  </requires>
  <extension point="xbmc.python.pluginsource" library="addon.py">
    <provides>audio</provides>
  </extension>
  <extension point="xbmc.addon.metadata">
    <summary lang="en">Music Box</summary>
    <summary lang="es">Music Box</summary> 
    <description lang="en">Music box is a new way to listen and discover music thought KODI.</description>
    <description lang="es">Music box es una nueva forma de escuchar y descubrir música a través de Kodi.</description>
    <language>en</language>
    <platform>all</platform>
  </extension>
</addon>
<?xml version="1.0" encoding="UTF-8"?>
<addon id="plugin.program.sgs.notifications" version="1.0.2"
       name="Stargate Notify" provider-name="SGS">
  <requires>
  	<import addon="xbmc.python" version="2.1.0"/>
  	<import addon="script.module.addon.common" optional="true" />
  </requires>
  <extension point="xbmc.python.script" library="default.py">
    <provides>executable</provides>
  </extension>
  <extension point="xbmc.service" library="service.py" start="startup">
  </extension>
  <extension point="xbmc.addon.metadata">
  	<summary>SGS News</summary>
  	<description>Receive Important SGS Notifications. Unsubscribe within Add-on Settings.</description>
  	<disclaimer>We take no responsibility for any problems this plugin might in any way, form, shape or size cause.</disclaimer>
  	<language>en</language>
  	<platform>all</platform>
  	<forum>buildscommunity.info</forum>
  	<website>-</website>
  	<source></source>
  	<email></email>
  </extension>
</addon>
<?xml version="1.0" encoding="UTF-8" standalone="yes"?>
<addon id="plugin.program.super.favourites" name="Super Favourites" version="1.0.59" provider-name="spoyser">
  <requires>
    <import addon="xbmc.python" version="2.14.0"/>
    <import addon="script.module.metahandler" optional="true" />
  </requires>


  <extension point="xbmc.python.pluginsource" library="default.py">
        <provides>video audio image executable</provides>
  </extension>

  
  <extension point="xbmc.service" library="service.py" start="startup" />

  
  <extension point="xbmc.addon.metadata">
    <summary lang="en">Put all your favourites bits of all your favourites addons into one easy to use addon.</summary>
    <description lang="en">Super Favourites is a better way of managing your Kodi Favourites.[CR][CR]Virtually any menu item within Kodi can be added to Super Favourites, even from addons that don't normally provide this feature.[CR][CR]Super Favourites allows you to better manage your Kodi favourites, including the creation of sub-folders, into which your Kodi favourites can then be copied or moved into.[CR][CR]This allows you to create you own custom addon with just the best bits of your favourite addons. Search your favourite addons, play your favourite music, read your favourite comic strips, select your favourite playlists, browse your favourite movies, listen to your favourite radio stations, watch your favourite cartoons, the possibilities are endless, all from within one easy to use addon.</description>
    <platform>all</platform>
    <language>en</language>
    <license>GNU GENERAL PUBLIC LICENSE. Version 2, June 1991</license>
    <forum>http://forum.xbmc.org/showthread.php?tid=192662</forum>
    <website></website>
    <source>https://github.com/spoyser/spoyser-repo/tree/master/plugin.program.super.favourites</source>
    <email>seanpoyser at gmail.com</email>

    <news>
1.0.59: 29th May 2017
    - 'Now playing' text now defined by SF due to skin variations
    </news>

  </extension>


  <extension point="kodi.context.item">
    <menu id="kodi.core.main">

      <item library="capture.py">
        <label>$ADDON[plugin.program.super.favourites 30002]</label>
        <visible>!IsEmpty(Window(Home).Property(SF_STD_CONTEXTMENU_ENABLED)) + !StringCompare(Container.PluginName,plugin.program.super.favourites)</visible>
      </item>

      <item library="menu_addtofaves.py">
        <label>$ADDON[plugin.program.super.favourites 30047]</label>
        <visible>!IsEmpty(Window(Home).Property(SF_STD_ADDTOFAVES_ENABLED)) + !StringCompare(Container.PluginName,plugin.program.super.favourites)</visible>
      </item>

      <item library="menu_download.py">
        <label>$ADDON[plugin.program.super.favourites 30259]</label>
        <visible>!IsEmpty(Window(Home).Property(SF_STD_DOWNLOAD_ENABLED)) + Player.IsInternetStream</visible>
      </item>

    </menu>
  </extension>

</addon>
<?xml version="1.0" encoding="UTF-8"?>
<addon id="plugin.program.tardis-fixtures"
version="1.0.26"
name="Tardis Fixtures"
provider-name="Wardoctor, primaeval">
<requires>
  <import addon="xbmc.python" version="2.20.0"/>
  <import addon="script.module.xbmcswift2" version="2.4.0"/>
  <import addon="script.module.requests" version="2.9.1" />
  <import addon="script.module.beautifulsoup4" />
  <import addon="script.module.dateutil" version="2.4.2" />
</requires>
<extension point="xbmc.python.pluginsource" library="main.py">
  <provides>executable</provides>
</extension>
<extension point="xbmc.addon.metadata">
  <summary lang="en">Tardis Fixtures</summary>
  <description lang="en">Tardis Fixtures with Channel Information.</description>
  <disclaimer lang="en">This addon provides NO stream content</disclaimer>
</extension>
</addon>
<?xml version="1.0" encoding="UTF-8" standalone="yes"?>
<addon id="plugin.video.covenant" version="8.1.31" name="Covenant" provider-name="Covenant">
	<requires>
		<import addon="xbmc.python" version="2.19.0" />
		<import addon="script.module.covenant" />
		<import addon="script.covenant.artwork" version="1.0.0" />
		<import addon="script.covenant.metadata" version="1.0.0" />
		<import addon="script.module.urlresolver" version="3.0.0" />
		<import addon="script.module.requests" />
		<import addon="script.module.metahandler" version="1.0.0" />
	</requires>
	<extension point="xbmc.python.pluginsource" library="covenant.py">
		<provides>video</provides>
	</extension>
	<extension point="xbmc.service" library="service.py" start="startup" />
	<extension point="xbmc.addon.metadata">
		<summary lang="en">Covenant</summary>
		<description lang="en">[I]A New Generation[/I][CR][CR][B]Covenant Movies and TV[/B][CR][CR]This addon does not form part of the Kodi Media Centre. Please do not seek assistance with this addon from any of the Official Kodi Support Channels.[CR][CR]The author does not host any of the content in this addon and takes no responsibility for content found.</description>
		<description lang="hr">[I]Nova generacija[/I][CR][CR][B]Covenant Filmova i TV serija[/B][CR][CR]Ovaj dodatak ne sadrži dijelove Kodi Medijskog Centra. Ne tažite pomoć za ovaj dodatak na službenim kanalima podrške za Kodi.[CR][CR]Autor ne posjeduje bilo kakav sadržaj u ovom dodatku i ne preuzima bilo kakvu odgovornost za pronađeni sadržaj.</description>
		<description lang="he">[I]הדור החדש[/I][CR][CR][B]Covenant סרטים וסדרות[/B][CR][CR]ההרחבה הזו אינה חלק של Kodi Media Center. אנא אל תבקש עזרה עם ההרחבה זה מכל אחד מערוצי התמיכה הרשמיים של Kodi [CR][CR]. אין למחבר תוכן בהרחבה הזו והמחבר אינו אחראי לתוכן שנמצא.</description>
		<platform>all</platform>
		<license>GNU GENERAL PUBLIC LICENSE. Version 3, 29 June 2007</license>
		<forum></forum>
		<website></website>
		<source></source>
		<disclaimer lang="en">The author of this addon do not host any of the content which is found and have no affiliation with any of the content providers. This addon simply searches websites for content. Use at your own risk!</disclaimer>
		<disclaimer lang="hr">Autor ovog dodatka ne posjeduje bilo kakav sadržaj koji je pronađen i nije povezan sa bilo kojim izvorom sadržaja. Ovaj dodatak samo pretražuje sadržaj na web stranicama. Koristite ga na vlastitu odgovornost!</disclaimer>
		<disclaimer lang="he">מחבר ההרחבה זה אינו מארח את התוכן שיתכן ויימצא ואין לו זיקה לאף אחד מספקי התוכן. הרחבה רק מחפשת תוכן שקיים באתרי אינטרנט. השימוש בהרחבה הוא על אחריותך בלבד!</disclaimer>
		<assets>
			<icon>icon.png</icon>
			<fanart>fanart.jpg</fanart>
    			<screenshot>resources/screenshots/screenshot-01.jpg</screenshot>
    			<screenshot>resources/screenshots/screenshot-02.jpg</screenshot>
    			<screenshot>resources/screenshots/screenshot-03.jpg</screenshot>
		</assets>
		<news></news>
	</extension>
</addon>
<?xml version="1.0" encoding="UTF-8" standalone="yes"?>
<addon id="plugin.video.master.catchup" name="Master Catchup" version="1.0.5" provider-name="Wardoctor">
  <requires>
    <import addon="xbmc.python" version="2.1.0"/>
  </requires>
  <extension point="xbmc.python.pluginsource" library="default.py">
        <provides>video</provides>
  </extension>
  <extension point="xbmc.addon.metadata">
    <summary lang="en">Master Catchup</summary>
    <description lang="en">Watch All Your Favourite UK TV Catchup</description>
    <platform>all</platform>
  </extension>
</addon>
<?xml version="1.0" encoding="UTF-8" standalone="yes"?>
<addon id="plugin.video.exodus" version="8.1.08" name="Exodus" provider-name="Wardoctor, Exodus">
	<requires>
		<import addon="xbmc.python" version="2.19.0" />
		<import addon="script.module.exodus" />
		<import addon="script.exodus.artwork" version="8.0.7" />
		<import addon="script.exodus.metadata" version="8.0.2" />
		<import addon="script.module.urlresolver" version="3.0.0" />
		<import addon="script.module.requests" />
		<import addon="script.module.metahandler" version="1.0.0" />
	</requires>
	<extension point="xbmc.python.pluginsource" library="exodus.py">
		<provides>video</provides>
	</extension>
	<extension point="xbmc.service" library="service.py" start="startup" />
	<extension point="xbmc.addon.metadata">
		<summary lang="en">Exodus</summary>
		<description lang="en">Exodus Modded to remove spam addons and to work</description>
		<disclaimer lang="en">The author does not host or distribute any of the content displayed by this addon. The author does not have any affiliation with the content provider.</disclaimer>
		<platform>all</platform>
		<license>GNU GENERAL PUBLIC LICENSE. Version 3, 29 June 2007</license>
		<forum></forum>
		<website></website>
		<assets>
			<icon>icon.png</icon>
			<fanart>fanart.jpg</fanart>
    			<screenshot>resources/screenshots/screenshot-01.jpg</screenshot>
    			<screenshot>resources/screenshots/screenshot-02.jpg</screenshot>
    			<screenshot>resources/screenshots/screenshot-03.jpg</screenshot>
		</assets>
		<news></news>
	</extension>
</addon>
<?xml version="1.0" encoding="UTF-8" standalone="yes"?>
<addon id="plugin.video.master.reborn" version="1.0.6" name="Master Reborn" provider-name="Wardoctor">
    <requires>
        <import addon="xbmc.python" version="2.19.0"/>
        <import addon="script.master-reborn.artwork" version="1.0.1"/>
		<import addon="script.master.metadata" version="1.0.1"/>
        <import addon="script.module.urlresolver" version="2.10.0"/>
        <import addon="script.module.metahandler" version="2.9.0"/>
        <import addon="script.module.requests" version="2.12.4"/>
        <import addon="script.module.beautifulsoup" version="3.2.1"/>
        <import addon="script.module.master.common" version="1.1.2"/>
        <import addon="script.module.futures" version="2.2.0"/>
        <import addon="script.module.nanscrapers" version="0.5.35"/>
    </requires>
    <extension point="xbmc.python.pluginsource" library="master.py">
        <provides>video</provides>
    </extension>
    <extension point="xbmc.addon.metadata">
        <summary lang="en">Master Reborn movies and TV shows</summary>
        <description lang="en">Watch movies and TV shows in high quality! Please note that this addon is not an official part of the Kodi media player and is therefore not to be mentioned within Kodi's official support channels. This addon has nothing to do with the media player itself, nor its intended use, it is simply a third party plugin which has been added to your system.</description>
        <disclaimer lang="en">The author does not host any content, nor is he affiliated with any of the content providers.</disclaimer>
        <platform>all</platform>
        <news></news>
        <assets>
            <icon>icon.png</icon>
            <fanart>fanart.jpg</fanart>
        </assets>
    </extension>
</addon>
<?xml version="1.0" encoding="UTF-8" standalone="yes"?>
<addon id="plugin.video.metalliq" name="MetalliQ" version="8.0.16" provider-name="Wardoctor, OpenELEQ, Midraal">
	<requires>
		<import addon="xbmc.python" version="2.19.0"/>
		<import addon="script.module.requests" version="2.9.1"/>
		<import addon="script.module.futures" version="2.2.0"/>
	</requires>
	<extension point="xbmc.python.pluginsource" library="default.py">
		<provides>video audio</provides>
	</extension>
	<extension point="xbmc.service" library="service.py" start="[login|startup]">
	</extension>
	<extension point="kodi.context.item">
		<menu id="kodi.core.main">
			<menu>
				<label>MetalliQ</label>
				<item library="context_toggle.py">
					<label>Preferred toggle</label>
					<visible>!System.HasAddon(context.metalliq) + !Skin.HasSetting(Toggling)</visible>
				</item>
				<item library="context_movie.py">
					<label>$ADDON[plugin.video.metalliq 30602]</label>
					<visible>StringCompare(ListItem.dbtype,movie) + SubString(ListItem.Path, plugin.video.metalliq)</visible>
				</item>
				<item library="context_tvshow.py">
					<label>$ADDON[plugin.video.metalliq 30602]</label>
					<visible>StringCompare(ListItem.dbtype,tvshow) + SubString(ListItem.Path, plugin.video.metalliq)</visible>
				</item>
				<item library="context_live.py">
					<label>$ADDON[plugin.video.metalliq 30602]</label>
					<visible>[SubString(ListItem.FileNameAndPath, plugin.video.metalliq\\Live) | SubString(ListItem.FileNameAndPath, plugin.video.metalliq\\Live)]</visible>
				</item>
				<item library="context_playable.py">
					<label>$ADDON[plugin.video.metalliq 30622]</label>
					<visible>!System.HasAddon(context.metalliq) + !Skin.HasSetting(Contexting)</visible>
				</item>
			</menu>
		</menu>
	</extension>
	<extension point="xbmc.addon.metadata">
		<platform>all</platform>
		<language></language>
		<summary lang="en">TMDb, TVDb, Trakt, AudioDb and LastFM browser</summary>
		<description lang="en">Browse The MovieDb, The TVDb, Trakt, The AudioDb and LastFM and pass info along to library or an addon to try and play it. Needs player-files and the appropriate addon to actually play.</description>
		<summary lang="nl">Blader door TMDb, TVDb, Trakt, AudioDb en LastFM</summary>
		<description lang="nl">Blader door The MovieDb, The TVDb, Trakt, The AudioDb en LastFM en geef info door aan de bibliotheek of een addon om te proberen het af te spelen. Vereist player-bestanden en de bijbehorende addon om daadwerkelijk af te kunnen spelen.</description>
		<supportedcontent>
			<content>movies</content>
			<content>tvshows</content>
			<content>episodes</content>
			<content>musicvideos</content>
			<content>music</content>
			<content>livetv</content>
		</supportedcontent>
		<genre>movies,tv,music,livetv</genre>
		<!--<video_guide>yt-id</video_guide>
		<video_preview>yt-id</video_preview>-->
		<forum></forum>
		<source></source>
		<email></email>
		<news></news>
	</extension>
</addon>
<?xml version="1.0" encoding="UTF-8" standalone="yes"?>
<addon id="plugin.video.missy" name="Missy" version="1.0.2" provider-name="Wardoctor, midraal">
    <requires>
        <import addon="xbmc.python" version="2.19.0" />
        <import addon="script.module.nanscrapers" version="0.5.5" />
        <import addon="script.module.python.koding.aio" version="0.9.6.6" />
        <import addon="script.module.beautifulsoup" version="3.2.1" />
        <import addon="script.module.requests" version="2.9.1" />
        <import addon="script.module.addon.common" version="2.0.0" />
        <import addon="script.module.xmltodict" version="0.9.0" />
        <!--<import addon="script.module.web-pdb" version="1.0"/>-->
        <import addon="script.module.urlresolver" version="1.2.0" />
    </requires>
    <extension point="xbmc.python.pluginsource" library="default.py">
        <provides>audio video</provides>
    </extension>
    <extension point="xbmc.service" library="service.py" start="[login|startup]" />
    <extension point="xbmc.addon.metadata">
        <summary lang="en">I'm in no hurry, I've got all day. And I'm not going to kill you until you say..something...nice.</summary>
        <description lang="en">Missy [COLOR red]##### CURRENTLY UNDER CONSTRUCTION #####[/COLOR]</description>
        <platform>all</platform>
        <forum></forum>
        <website></website>
        <video_guide></video_guide>
        <video_preview></video_preview>
    </extension>
</addon>
<?xml version="1.0" encoding="UTF-8" standalone="yes"?>
<addon id="plugin.video.oculus" name="Oculus" version="1.5" provider-name="trademark">
    <requires>
        <import addon="xbmc.python" version="2.19.0" />
        <import addon="script.module.nanscrapers" version="0.5.5" />
        <import addon="script.module.python.koding.aio" version="0.9.6.6" />
        <import addon="script.module.beautifulsoup" version="3.2.1" />
        <import addon="script.module.requests" version="2.9.1" />
        <import addon="script.module.addon.common" version="2.0.0" />
        <import addon="script.module.xmltodict" version="0.9.0" />
        <import addon="script.module.urlresolver" version="1.2.0" />
    </requires>
    <extension point="xbmc.python.pluginsource" library="default.py">
        <provides>video</provides>
    </extension>
    <extension point="xbmc.service" library="service.py" start="[login|startup]" />
    <extension point="xbmc.addon.metadata">
        <summary lang="en">Trademark TMB</summary>
        <description lang="en">Trademark TMB Entertainment</description>
        <platform>all</platform>
		<forum>http://noobsandnerds.com/support/forumdisplay.php?fid=253</forum>
        <website>www.noobsandnerds.com</website>
        <video_guide>xtOqLY5PJDY</video_guide>
		<video_preview>WdKIzaiBBI</video_preview>
    </extension>
</addon>
<?xml version="1.0" encoding="UTF-8" standalone="yes"?>
<addon id="plugin.video.rebirth" version="8.0.2" name="Rebirth" provider-name="Wardoctor, Cypher">
	<requires>
		<import addon="xbmc.python" version="2.19.0" />
		<import addon="script.rebirth.artwork" version="1.0.0" />
		<import addon="script.rebirth.metadata" version="1.0.0" />
                <import addon="script.module.urlresolver"/>
                <import addon="script.module.metahandler"/>
                <import addon="script.module.requests"/>
                <import addon="script.module.beautifulsoup"/>
                <import addon="script.module.schism.common"/>
                <import addon="script.module.futures"/>
                <import addon="script.module.nanscrapers" version="0.5.5" />
	</requires>
	<extension point="xbmc.python.pluginsource" library="Rebirth.py">
		<provides>video</provides>
	</extension>
	<extension point="xbmc.service" library="service.py" start="startup" />
	<extension point="xbmc.addon.metadata">
		<summary lang="en">Rebirth. Modded for Intergration</summary>
		<description lang="en">The Ultimate Movie, TV Show, and Playlist Add-on</description>
		<disclaimer lang="en">The author does not host or distribute any of the content displayed by this addon. The author does not have any affiliation with the content provider.</disclaimer>
		<platform>all</platform>
		<forum></forum>
		<website></website>
		<source></source>
		<assets>
			<icon>icon.png</icon>
			<fanart>fanart.jpg</fanart>
		</assets>
		<news></news>
	</extension>
</addon>
<addon id="plugin.video.salts" version="8.0.205" name="Stream All The Sources" provider-name="Wardoctor, k3l3vra">
    <requires>
        <import addon="xbmc.python" version="2.19.0"/>
        <import addon="script.module.urlresolver" version="3.0.0"/>
        <import addon="script.module.myconnpy" version="1.1.6" />
        <import addon="script.module.tknorris.shared" version="8.0.19"/>
        <import addon="script.module.six"/>
        <import addon="script.module.dateutil"/>
    </requires>
    <extension point="xbmc.python.pluginsource" library="default.py">
        <provides>video</provides>
    </extension>
     <extension point="xbmc.service" library="service.py" start="startup"/>
    <extension point="xbmc.addon.metadata">
        <summary>Last Version Made From The TVA Guys, modified</summary>
        <description>Modified and version bumped to prevent update from rogue repos</description>
        <platform>all</platform>
	</extension>
</addon>
<?xml version="1.0" encoding="UTF-8"?>
<addon id="plugin.video.saltsrd.lite" version="8.0.234" name="Salts RD Lite" provider-name="XvBMC-NL">
    <requires>
        <import addon="xbmc.python" version="2.19.0"/>
        <import addon="script.module.futures" version="2.2.0"/>                             <!--    NEW     -->
        <import addon="script.module.metahandler" version="3.0.2" />                        <!--    NEW     -->
        <import addon="script.module.pyxbmct" version="1.2.0"/>                             <!--    NEW     -->
        <import addon="script.module.dateutil" version="2.5.3"/>
        <import addon="script.module.myconnpy" version="1.1.7"/>
        <import addon="script.module.saltsrd.shared" version="0.0.23"/>  <!-- script.module.tknorris.shared -->
        <import addon="script.module.six" version="1.9.0"/>
        <import addon="script.module.urlresolver" version="4.0.07"/>
    </requires>
    <extension point="xbmc.python.pluginsource" library="default.py">
        <provides>video</provides>
    </extension>
        <extension point="xbmc.service" library="service.py" start="startup"/>
    <extension point="xbmc.addon.metadata">
        <summary>Stream video from many difference sources with XvBMC SALTs RD Lite (RealDebrid)</summary>
        <description>This is the MOD version of SALTs by XvBMC -4- RealDebrid usage (also a big thx to: TKnorris/k3l3vra/Cypher/MR.Blamo)</description>
        <disclaimer>MOD info @ http://bit.ly/XvBMC-NL (USE_AT_YOUR_OWN!_RISK!) ---> *C*R*E*D*I*T*S* TKnorris/k3l3vra/Cypher/MR.Blamo</disclaimer>
        <platform>all</platform>
        <license>GNU GENERAL PUBLIC LICENSE. Version 3, June 2007</license>
        <forum></forum>
        <website></website>
        <source></source>
        <news>[B]Version 8.0.233[/B]: Modded</news>
        <assets>
          <icon>icon.png</icon>
          <fanart>fanart.jpg</fanart>
        </assets>
    </extension>
</addon>
<?xml version="1.0" encoding="UTF-8" standalone="yes"?>
<addon id="plugin.video.stargate-streams" version="2.0.7" name="Stargate Streams" provider-name="Wardoctor">
    <requires>
        <import addon="xbmc.python" version="2.1.0"/>
		<import addon="plugin.program.sgs.notifications" version="1.0.2" />        
    </requires>
    <extension point="xbmc.python.pluginsource" library="default.py">
        <provides>video</provides>
    </extension>
    <extension point="xbmc.addon.metadata">
        <summary>Stargate Streams</summary>
        <description>Stargate Streams</description>
        <disclaimer>The author does not host or distribute any of the content displayed by this addon. The author does not have any affiliation with the content providers.</disclaimer>
        <language>en</language>
        <platform>all</platform>
        <source></source>
        <email></email>
    </extension>
</addon>
<?xml version="1.0" encoding="UTF-8" standalone="yes"?>
<addon id="plugin.video.tardis.tvcatchup" name="TV Catchup Tardis Edition" version="1.3.7" provider-name="Wardoctor, beardypig">
  <requires>
    <import addon="xbmc.python" version="2.19.0"/>
    <import addon="script.module.six" version="1.9.0"/>
  </requires>
 <extension point="xbmc.python.pluginsource" library="addon.py">
    <provides>video</provides>
  </extension>
  <extension point="xbmc.addon.metadata">
    <summary lang="en">Live streams from TVCatchup.com</summary>
    <disclaimer>May not work outside the UK</disclaimer>
    <platform>all</platform>
    <forum></forum>
    <source></source>
  </extension>
</addon>
<?xml version="1.0" encoding="UTF-8"?>
<addon id="plugin.video.tfixtures.listings"
version="1.0.3"
name="Tardis Fixtures Listings"
provider-name="Wardoctor, primaeval">
<requires>
  <import addon="xbmc.python" version="2.20.0"/>
  <import addon="script.module.xbmcswift2" version="2.4.0"/>
  <import addon="script.module.requests" version="2.9.1" />
</requires>
<extension point="xbmc.python.pluginsource" library="main.py">
  <provides>video</provides>
</extension>
<extension point="xbmc.service" library="service.py" start="login"/>
<extension point="xbmc.addon.metadata">
  <summary lang="en">Tardis Fixtures Listings</summary>
  <description lang="en">Tardis Fixtures Listings.</description>
  <disclaimer lang="en">.</disclaimer>
</extension>
</addon>
<?xml version="1.0" encoding="UTF-8" standalone="yes"?>
<addon id="plugin.video.ukturk" name="UK Turk Playlists" version="4.0.14" provider-name="UKTurk">
  <requires>
    <import addon="script.module.simplejson" version="3.3.0"/>
    <import addon="xbmc.python" version="2.1.0"/>
    <import addon="script.module.t0mm0.common" version="2.0.0"/>
    <import addon="plugin.video.youtube" version="3.0.0"/>
    <import addon="script.module.urlresolver"  version="2.1.2"/>
    <import addon="script.common.plugin.cache" version="2.5.2"/>
    <import addon="script.module.metahandler" version="2.5.1"/>    
    <import addon="script.video.F4mProxy" version="2.5.3"/>
    <import addon="script.module.liveresolver" version="0.1.24"/>
  </requires>
  <extension point="xbmc.python.pluginsource" library="default.py">
        <provides>video</provides>
  </extension>
  <extension point="xbmc.addon.metadata">
    <summary lang="en">Free Playlists courtesy of @uk_turk</summary>
    <description lang="en">Free Playlists courtesy of @uk_turk</description>
    <platform>all</platform>
  </extension>
</addon>
<?xml version="1.0" encoding="UTF-8" standalone="yes"?>
<addon id="plugin.video.uktvplay" name="UKTV Play" version="8.0.1" provider-name="Wardoctor">
  <requires>
    <import addon="xbmc.python" version="2.1.0"/>
  </requires>
  <extension point="xbmc.python.pluginsource" library="default.py">
        <provides>video</provides>
  </extension>
  <extension point="xbmc.addon.metadata">
    <summary lang="en">UKTV Play</summary>
    <description lang="en">Watch All Your Favourite UK TV from Dave,Really,Yesterday and Drama</description>
    <platform>all</platform>
  </extension>
</addon>
<?xml version="1.0" encoding="UTF-8" standalone="yes"?>
<addon id="plugin.video.uncoded" 
	version="8.2.4" 
	name="[COLOR springgreen]UNCODED[/COLOR]" 
	provider-name="[COLOR springgreen]UNCODED[/COLOR]">
	<requires>
		<import addon="xbmc.python" version="2.19.0" />
		<import addon="script.module.uncoded" />
		<import addon="script.uncoded.artwork" version="1.0.0" />
		<import addon="script.uncoded.metadata" version="1.0.0" />
		<import addon="script.module.urlresolver" version="3.0.0" />
		<import addon="script.module.requests" />
		<import addon="script.module.metahandler" version="1.0.0" />
	</requires>
	<extension point="xbmc.python.pluginsource" library="uncoded.py">
		<provides>video</provides>
	</extension>
	<extension point="xbmc.service" library="service.py" start="startup" />
	<extension point="xbmc.addon.metadata">
		<summary lang="en">UNCODED</summary>
		<description lang="en">[I]A New Generation[/I][CR][CR][B]UNCODED Movies and TV[/B][CR][CR]This addon does not form part of the Kodi Media Centre. Please do not seek assistance with this addon from any of the Official Kodi Support Channels.[CR][CR]The author does not host any of the content in this addon and takes no responsibility for content found.</description>
		<platform>all</platform>
		<license>GNU GENERAL PUBLIC LICENSE. Version 3, 29 June 2007</license>
		<forum></forum>
		<website></website>
		<source></source>
		<disclaimer lang="en">The author of this addon do not host any of the content which is found and have no affiliation with any of the content providers. This addon simply searches websites for content. Use at your own risk!</disclaimer>
		<assets>
			<news>Covenant is now rebranded by UNCODED.[CR]Will continu to work on this! I am a Noob dev, who wants to cooperate with other devs to preserve KODI add-ons.[CR]Looking for a home? We can help u out. Contact us!</news>
			<email>admin@uncoded.life</email>
			<icon>icon.png</icon>
			<fanart>fanart.jpg</fanart>
    			<screenshot>resources/screenshots/screenshot-01.jpg</screenshot>
    			<screenshot>resources/screenshots/screenshot-02.jpg</screenshot>
    			<screenshot>resources/screenshots/screenshot-03.jpg</screenshot>
		</assets>
		<news></news>
	</extension>
</addon>

<?xml version="1.0" encoding="UTF-8" standalone="yes"?>
<addon id="script.covenant.artwork" version="1.0.3" name="Covenant Artwork" provider-name="Covenant">
	<requires>
		<import addon="xbmc.python" version="2.19.0"/>
	</requires>
	<extension point="xbmc.python.module" library="lib" />
	<extension point="xbmc.addon.metadata">
		<summary>Themes for the Covenant Addon</summary>
		<description></description>
		<platform>all</platform>
	</extension>
</addon>
<?xml version="1.0" encoding="UTF-8" standalone="yes"?>
<addon id="script.covenant.metadata" version="1.0.2" name="Covenant Metadata" provider-name="Covenant">
	<requires>
		<import addon="xbmc.python" version="2.19.0"/>
	</requires>
	<extension point="xbmc.python.module" library="lib" />
	<extension point="xbmc.addon.metadata">
		<summary>Metadata for the Covenant Addon</summary>
		<description>Metadata for Covenant are maintained separately to make distribution of the the addon itself easier/faster.</description>
		<platform>all</platform>
	</extension>
</addon>
<?xml version="1.0" encoding="UTF-8" standalone="yes"?>
<addon id="script.exodus.artwork" version="8.0.7" name="Exodus Artwork" provider-name="Exodus">
	<requires>
		<import addon="xbmc.python" version="2.19.0"/>
	</requires>
	<extension point="xbmc.python.module" library="lib" />
	<extension point="xbmc.addon.metadata">
		<summary>Themes for the Exodus Addon</summary>
		<description></description>
		<platform>all</platform>
	</extension>
</addon>
<?xml version="1.0" encoding="UTF-8" standalone="yes"?>
<addon id="script.exodus.metadata" version="8.0.2" name="Exodus Metadata" provider-name="Exodus">
	<requires>
		<import addon="xbmc.python" version="2.19.0"/>
	</requires>
	<extension point="xbmc.python.module" library="lib" />
	<extension point="xbmc.addon.metadata">
		<summary>Metadata for the Exodus Addon</summary>
		<description>Metadata for Exodus are maintained separately to make distribution of the the addon itself easier/faster.</description>
		<platform>all</platform>
	</extension>
</addon>
<?xml version="1.0" encoding="UTF-8" standalone="yes"?>
<addon id="script.extendedinfo" name="Extended Info Mod" version="8.0.4" provider-name="ReModded by Wardoctor, Modded by OpenELEQ, original work by phil65">
  <requires>
    <import addon="xbmc.python"                     version="2.19.0"/>
    <import addon="plugin.program.super.favourites" version="1.0.48"/>
    <import addon="plugin.video.metalliq"           version="8.0.16"/>
    <import addon="plugin.video.youtube"            version="5.3.10"/>
    <import addon="script.module.pil"               version="1.1.7"/>
    <import addon="script.module.requests"          version="1.1.0"/>
    <import addon="script.module.simplejson"        version="2.0.10"/>
    <import addon="script.module.urlresolver"       version="1.0.0"/>
    <import addon="script.module.youtube.dl"        version="14.519.1"/>
  </requires>
  <extension point="xbmc.python.script"             library="default.py">
    <provides>executable</provides>
  </extension>
  <extension point="xbmc.python.library"            library="default.py" />
  <extension point="xbmc.python.pluginsource"       library="plugin.py">
    <provides>video</provides>
  </extension>
  <extension point="xbmc.addon.metadata">
    <language/>
    <summary lang="en">Extended Info ReMod</summary>
    <description lang="en">This script offers various possibilities to display online content inside skins as well as a complete MovieDB browser including info dialogs for various media types. Used services are themoviedb.org, theaudiodb.org, Trakt.TV, omdbapi.com and a lot more. Needs skin implementation for lot of functions. Uses MetalliQ for playback and library functions.</description>
    <summary lang="nl">Extended Info Mod</summary>
    <description lang="nl">Dit script biedt meerdere mogelijkheden om online content weer te geven in skins en bevat ook een complete MovieDB browser inclusief info dialogen voor verscheidene media types. Gebruikte diensten zijn themoviedb.org, theaudiodb.org, Trakt.TV, omdbapi.com en nog veel meer. Vereist skin implementatie voor de meeste functies. Gebruikt MetalliQ voor afspeel en bibliotheek functies.</description>
    <platform>all</platform>
    <genre>movies,tv,trailers</genre>
    <video_guide></video_guide>
    <video_preview></video_preview>
    <license>GNU GENERAL PUBLIC LICENSE Version 2, June 1991</license>
    <forum></forum>
    <source></source>
    <email></email>
  </extension>
</addon>
<?xml version="1.0" encoding="UTF-8" standalone="yes"?>
<addon id="script.master-reborn.artwork" version="1.0.1" name="Master Reborn Artwork" provider-name="Wardoctor">
	<requires>
		<import addon="xbmc.python" version="2.19.0"/>
	</requires>
	<extension point="xbmc.python.script" library="default.py">
		<provides>executable</provides>
	</extension>
	<extension point="xbmc.addon.metadata">
		<summary>Themes for the Master Reborn Addon</summary>
		<description></description>
		<platform>all</platform>
		<news>Added new artwork</news>
	</extension>
</addon>
<?xml version="1.0" encoding="UTF-8" standalone="yes"?>
<addon id="script.module.covenant" name="Covenant Module" version="8.00.026" provider-name="Covenant">
	<requires>
		<import addon="xbmc.python" version="2.1.0" />
	</requires>
	<extension point="xbmc.python.module" library="lib" />
	<extension point="xbmc.addon.metadata">
		<platform>all</platform>
		<summary lang="en">Covenant</summary>
	</extension>
</addon>
<?xml version="1.0" encoding="UTF-8" standalone="yes"?>
<addon id="script.module.exodus" name="Exodus Module" version="8.00.026" provider-name="Exodus">
	<requires>
		<import addon="xbmc.python" version="2.1.0" />
	</requires>
	<extension point="xbmc.python.module" library="lib" />
	<extension point="xbmc.addon.metadata">
		<platform>all</platform>
		<summary lang="en">Exodus</summary>
	</extension>
</addon>
<?xml version="1.0" encoding="UTF-8" standalone="yes"?>
<addon id="script.module.liveresolver" 
     name="LiveResolver" 
     version="0.1.49" 
     provider-name="natko1412">
  <requires>
    <import addon="xbmc.python" version="2.1.0" />
    <import addon="script.module.beautifulsoup" version="3.2.1"/>
    <import addon="script.module.requests"/>
    <import addon="script.module.addon.common" version="2.0.0" />

  </requires>
  <extension point="xbmc.python.module" library="lib" />
  <extension point="xbmc.addon.metadata">
    <platform>all</platform>
    <summary lang="en">Resolve common live video host URL's to be playable in XBMC/Kodi + find links embeded in sites.</summary>
    <description lang="en"></description>    
  </extension>
</addon>
<?xml version="1.0" encoding="UTF-8" standalone="yes"?>
<addon id="script.module.master.common" name="Master Reborn Common Libraries" version="1.1.2" provider-name="Wardoctor">
	<requires>
		<import addon="xbmc.python" version="2.1.0" />
		<import addon="script.module.six" />
		<import addon="script.module.metahandler" />
		<import addon="script.module.beautifulsoup" />
	</requires>
	<extension point="xbmc.python.module" library="lib" />
	<extension point="xbmc.addon.metadata">
		<platform>all</platform>
		<summary lang="en">Collection of modules used by Master Reborn</summary>
		<description lang="en">Collection of modules used by Master Reborn</description>
		<license>GNU GENERAL PUBLIC LICENSE. Version 2, June 1991</license>
	</extension>
</addon>
<?xml version="1.0" encoding="UTF-8" standalone="yes"?>
<addon id="script.master.metadata" version="1.0.1" name="Master Metadata" provider-name="Wardoctor">
	<requires>
		<import addon="xbmc.python" version="2.19.0"/>
	</requires>
	<extension point="xbmc.python.module" library="lib" />
	<extension point="xbmc.addon.metadata">
		<summary>Metadata for the Master Addon</summary>
		<description>Metadata for Master are maintained separately to make distribution of the the addon itself easier/faster.</description>
		<platform>all</platform>
	</extension>
</addon>
<?xml version="1.0" encoding="UTF-8" standalone="yes"?>
<addon id="script.module.metahandler" 
     name="metahandler" 
     version="3.0.2" 
     provider-name="Eldorado, jsergio">
  <requires>
    <import addon="xbmc.python" version="2.1.0" />
    <import addon="script.module.simplejson" version="3.3.0"/>
    <import addon="script.module.addon.common" version="2.0.0"/>
    <import addon="script.module.myconnpy" version="1.1.6"/>
  </requires>
  <extension point="xbmc.python.module" library="lib" />
  <extension point="xbmc.addon.metadata">
    <summary lang="en">Downloads Artwork for TV shows, Movies and Music videos for addons and stores them in a local SQLITE database</summary>
    <description lang="en">Queries, stores, and returns metadata for TV shows, Movies and Musicvideos. [CR]Sources:[CR]www.thetvdb.com[CR]www.themoviedb.org[CR]www.imdb.com[CR]www.omdbapi.com[CR]This product uses the TMDb API but is not endorsed or certified by TMDb.</description>
    <disclaimer lang="en"></disclaimer>
    <language></language>
    <platform>all</platform>
    <license>GNU GENERAL PUBLIC LICENSE. Version 2, June 1991</license>
    <forum></forum>
    <website></website>
    <email></email>
    <source></source>
  </extension>
</addon>
<?xml version="1.0" encoding="UTF-8" standalone="yes"?>
<addon id="script.module.nanscrapers" name="NaN Scrapers" version="0.5.41" provider-name="Team NaN">
        <requires>
                <import addon="xbmc.python" version="2.1.0"/>
                <import addon="script.module.beautifulsoup" version="3.2.1"/>
                <import addon="script.module.futures" version="2.2.0"/>
                <import addon="script.module.requests"/>
                <import addon="script.module.six"/>
                <!--<import addon="script.module.urlresolver" version="3.0.0" optional="true"/>-->
                <!--<import addon="script.mrknow.urlresolver" version="2016.10.30.2" optional="true"/>-->
        </requires>
        <extension point="xbmc.python.module" library="lib"/>
        <extension point="xbmc.python.pluginsource" library="lib/default.py">
                <provides>executable</provides>
        </extension>
        <extension point="xbmc.addon.metadata">
                <platform>all</platform>
                <summary lang="en">Scrape common video host for URL's to be playable in XBMC/Kodi.</summary>
                <description lang="en">Scrape common video host for URL's to be playable in XBMC/Kodi, simplifying addon development of video plugins requiring multi video hosts.
                </description>
                <license>GPL v3</license>
                <source>https://github.com/noobsandnerds/noobsandnerds/tree/master/script.module.nanscrapers</source>
                <forum>http://www.noobsandnerds.com/support/showthread.php?tid=17212</forum>
                <website>http://noobsandnerds.com</website>
        </extension>
</addon>
<?xml version="1.0" encoding="UTF-8" standalone="yes"?>
<addon id="script.module.pil"
       name="Python Image Library"
       version="1.1.7"
       provider-name="PythonWare">
  <requires>
    <import addon="xbmc.python" version="2.1.0"/>
  </requires>
  <extension point="xbmc.python.module"
             library="lib" />
  <extension point="xbmc.addon.metadata">
    <platform>all</platform>
  </extension>
</addon>
<?xml version="1.0" encoding="UTF-8" standalone="yes"?>
<addon id="script.module.python.koding.aio"
   name="Python Koding AIO"
   version="0.9.8.9"
   provider-name="Total Revolution, noobsandnerds">
  <requires>
    <import addon="xbmc.python" version="2.1.0"/>
    <import addon="script.module.urlresolver" version="1.2.0"/>
    <import addon="script.module.requests" version="2.3.0"/>
    <import addon="script.module.beautifulsoup" version="2.1.31"/>
  </requires>
  <extension point="xbmc.python.module" library="lib" />
  <extension point="xbmc.addon.metadata">
    <platform>all</platform>
    <summary lang="en">Python Koding All In One</summary>
    <description lang="en">Python Koding AIO contains a bunch of time saving modules that allows for quick and simple development. Although developed at totalrevolution.tv this also contains unique features which hook into the noobsandnerds.com framework so a big thanks to the team and users who keep the portals updated.</description>
    <disclaimer lang="en"></disclaimer>
    <language></language>
    <license>Creative Commons 4.0-NC-ND</license>
    <forum>http://noobsandnerds.com/support/showthread.php?tid=17614</forum>
    <website>http://totalrevolution.tv</website>
    <news>Added new Python_Version funtion and added BS dependency</news>
    <source>https://github.com/totalrevolution/totalrevolution/tree/master/script.module.python.koding.aio</source>
  </extension>
</addon>
<?xml version="1.0" encoding="UTF-8" standalone="yes"?>
<addon id="script.module.pyxbmct"
   name="PyXBMCt"
   version="1.2.0"
   provider-name="Roman V.M.">
  <requires>
    <import addon="xbmc.python" version="2.20.0"/>
  </requires>
  <extension point="xbmc.python.module" library="lib" />
  <extension point="xbmc.addon.metadata">
    <platform>all</platform>
    <summary lang="en">PyXBMCt UI framework</summary>
    <description lang="en">PyXBMCt is a mini-framework for simple XBMC addon UI buliding. It is similar to PyQt and provides parent windows, a number of UI controls (widgets) and a grid layout manager to place controls.</description>
    <disclaimer lang="en"></disclaimer>
    <language></language>
    <license>GNU GPL v.3</license>
    <forum>http://forum.xbmc.org/showthread.php?tid=174859</forum>
    <website>http://romanvm.github.io/PyXBMCt</website>
    <email>romanvm@yandex.ua</email>
    <source>https://github.com/romanvm/script.module.pyxbmct</source>
  </extension>  
</addon>
<?xml version="1.0" encoding="UTF-8" standalone="yes"?>
<addon id="script.module.saltsrd.shared" name="Salts RD Lite - Common Libraries" version="0.0.23" provider-name="XvBMC-NL">
	<requires>
		<import addon="xbmc.python" version="2.1.0" />
	</requires>
	<extension point="xbmc.python.module" library="lib" />
	<extension point="xbmc.addon.metadata">
		<platform>all</platform>
		<summary lang="en">Credits -2- TKnorris</summary>
	</extension>
</addon>
<?xml version="1.0" encoding="UTF-8" standalone="yes"?>
<addon id="script.module.schism.common" name="Master Reborn Common Libraries" version="1.1.1" provider-name="Wardoctor">
	<requires>
		<import addon="xbmc.python" version="2.1.0" />
		<import addon="script.module.six" />
		<import addon="script.module.metahandler" />
		<import addon="script.module.beautifulsoup" />
	</requires>
	<extension point="xbmc.python.module" library="lib" />
	<extension point="xbmc.addon.metadata">
		<platform>all</platform>
		<summary lang="en">Collection of modules used by Master Reborn</summary>
		<description lang="en">Collection of modules used by Master Reborn</description>
		<license>GNU GENERAL PUBLIC LICENSE. Version 2, June 1991</license>
	</extension>
</addon>
<?xml version="1.0" encoding="UTF-8" standalone="yes"?>
<addon id="script.module.tknorris.shared" name="TKNorris Common Libraries" version="8.0.23" provider-name="tknorris">
	<requires>
		<import addon="xbmc.python" version="2.1.0" />
	</requires>
	<extension point="xbmc.python.module" library="lib" />
	<extension point="xbmc.addon.metadata">
		<platform>all</platform>
		<summary lang="en">Reusable Modules used by several of tknorris's addons, modified</summary>
	</extension>
</addon>
<?xml version="1.0" encoding="UTF-8" standalone="yes"?>
<addon id="script.module.uncoded" name="Uncoded Module" version="8.0.0" provider-name="Uncoded">
	<requires>
		<import addon="xbmc.python" version="2.1.0" />
	</requires>
	<extension point="xbmc.python.module" library="lib" />
	<extension point="xbmc.addon.metadata">
		<platform>all</platform>
		<summary lang="en">Uncoded, Modded to Allow Metalliq Playback</summary>
	</extension>
</addon>
<?xml version="1.0" encoding="UTF-8" standalone="yes"?>
<addon id="script.module.urlresolver" name="URLResolver" version="4.0.12" provider-name="Eldorado, tknorris, tvaddons">
	<requires>
		<import addon="xbmc.python" version="2.1.0" />
		<import addon="plugin.video.youtube" optional="true" />
		<import addon="script.module.python.twitch" optional="true" />
		<import addon="script.module.cryptopy" version="1.2.6" optional="true" />
	</requires>
	<extension point="xbmc.python.module" library="lib" />
	<extension point="xbmc.python.pluginsource" library="lib/default.py" />
	<extension point="xbmc.addon.metadata">
		<platform>all</platform>
		<summary lang="en">Resolve common video host URL's to be playable in XBMC/Kodi.</summary>
		<summary lang="hr">Prilagodi najčešće URL-ove video izvora kako bi radili u XBMC/Kodiju.</summary>
		<description lang="en">Resolve common video host URL's to be playable in XBMC/Kodi, simplify addon development of video plugins requiring multi video hosts.</description>
		<description lang="hr">Prilagodi najčešće URL-ove video izvora kako bi radili u XBMC/Kodiju, pojednostavnjuje razvoj priključaka za video dodatke koji zahtjevaju višestruke video izvore.</description>
        <forum>https://www.tvaddons.co/forums</forum>
        <website>https://www.tvaddons.co</website>
	</extension>
</addon>
<?xml version="1.0" encoding="UTF-8" standalone="yes"?>
<addon id="script.rebirth.artwork" version="1.0.1" name="Rebirth Artwork" provider-name="Cypher">
	<requires>
		<import addon="xbmc.python" version="2.19.0"/>
	</requires>
	<extension point="xbmc.python.module" library="lib" />
	<extension point="xbmc.addon.metadata">
		<summary>Themes for the Rebirth Addon</summary>
		<description>Themes for Rebirth are maintained separately to make distribution of the the addon itself easier/faster.</description>
		<platform>all</platform>
	</extension>
</addon>
<?xml version="1.0" encoding="UTF-8" standalone="yes"?>
<addon id="script.rebirth.metadata" version="1.0.0" name="Rebirth Metadata" provider-name="Cypher">
	<requires>
		<import addon="xbmc.python" version="2.19.0"/>
	</requires>
	<extension point="xbmc.python.module" library="lib" />
	<extension point="xbmc.addon.metadata">
		<summary>Metadata for the Rebirth Addon</summary>
		<description>Metadata for Rebirth are maintained separately to make distribution of the the addon itself easier/faster.</description>
		<platform>all</platform>
	</extension>
</addon>
<?xml version="1.0" encoding="UTF-8" standalone="yes"?>
<addon id="script.service.caretaker" name="KN Addon Caretaker" version="9.9.9" provider-name="Birger Jesch">
    <requires>
        <import addon="xbmc.python" version="2.25.0"/>
        <import addon="xbmc.json" version="7.0.0"/>
    </requires>
    <extension point="xbmc.service" library="service.py" start="login"/>
    <extension point="xbmc.python.script" library="addon.py"/>
    <extension point="xbmc.addon.metadata">
        <summary lang="en_gb">Take care with unauthorized Repositories</summary>
        <description lang="en_gb">This service checks your addon folder for possibly unauthorized, potentially harmful repositories and informs the user about these. Detailed informations are logged into the caretaker.log at the same folder as your kodi.log. Repository providers: If you think your repository is mistakenly blacklisted, please inform the vendor of this addon.</description>
        <disclaimer lang="en_gb">Use at your own risk.</disclaimer>
        <summary lang="de_de">Vorsicht vor nicht autorisierten Repositories</summary>
        <description lang="de_de">Dieser Dienst überprüft den Addon-Ordner auf möglicherweise nicht autorisierte, potentiell schädliche Repositories und informiert den Nutzer darüber. Detaillierte Informationen werden im caretaker.log protokolliert, welche sich im Log-Verzeichnis von Kodi befindet. Repository Provider: Sollte Euer Repository fälschlicherweise auf der Blacklist erscheinen, informiert bitte den Anbieter dieses Addons.</description>
        <disclaimer lang="de_de">Benutzung auf eigene Gefahr.</disclaimer>
        <platform>all</platform>
        <license>GNU GENERAL PUBLIC LICENSE. Version 3, June 2007</license>
        <forum>https://www.kodinerds.net/index.php/Thread/57888-Release-script-service-caretaker/</forum>
        <website></website>
        <email>Birger.Jesch@gmail.com</email>
        <source>https://github.com/b-jesch/script.service.caretaker</source>
        <news></news>
        <assets>
            <icon>resources/icon.png</icon>
            <fanart></fanart>
            <screenshot></screenshot>
        </assets>
    </extension>
</addon>
<?xml version="1.0" encoding="UTF-8" standalone="yes"?>
<addon id="script.stargate.guide" name="Stargate Guide"
version="1.0.8" provider-name="Wardoctor">
    <requires>
        <import addon="xbmc.python" version="2.25.0"/>
        <import addon="script.module.simplejson" version="3.3.0"/>
        <import addon="script.module.requests" version="2.9.1" />
        <import addon="script.module.dateutil" version="2.4.2" />
        <import addon="script.module.pil" />
        <import addon="script.module.beautifulsoup4" />
    </requires>
    <extension point="xbmc.python.script" library="addon.py">
            <provides>executable</provides>
    </extension>
    <extension point="xbmc.service" library="service.py" start="login"/>
    <extension point="xbmc.addon.metadata">
        <description lang="en">TV Guide especially for Stargate Streams. Based on Fullscreen TV Guide with major contributions from: primaeval, iainmacleod, im85288, RayW1986, bluezed, andy, Zomboided, tycoo, kjb86.</description>
        <disclaimer lang="en">Based on the original TV Guide addon by twinther, FTV Guide and Midraal's fork.</disclaimer>
        <language></language>
        <platform>all</platform>
        <license>GPLv2</license>
        <forum></forum>
        <source></source>
        <website></website>
        <email></email>
        <news>
        </news>
    </extension>
</addon>
<?xml version="1.0" encoding="UTF-8" standalone="yes"?>
<addon id="script.uncoded.artwork" version="1.0.0" name="Uncoded Artwork" provider-name="Uncoded">
	<requires>
		<import addon="xbmc.python" version="2.19.0"/>
	</requires>
	<extension point="xbmc.python.module" library="lib" />
	<extension point="xbmc.addon.metadata">
		<summary>Themes for the Uncoded Addon</summary>
		<description></description>
		<platform>all</platform>
	</extension>
</addon>
<?xml version="1.0" encoding="UTF-8" standalone="yes"?>
<addon id="script.uncoded.metadata" version="1.0.0" name="Uncoded Metadata" provider-name="Uncoded">
	<requires>
		<import addon="xbmc.python" version="2.19.0"/>
	</requires>
	<extension point="xbmc.python.module" library="lib" />
	<extension point="xbmc.addon.metadata">
		<summary>Metadata for the Uncoded Addon</summary>
		<description>Metadata for Uncoded are maintained separately to make distribution of the the addon itself easier/faster.</description>
		<platform>all</platform>
	</extension>
</addon>
<?xml version="1.0" encoding="UTF-8" standalone="yes"?>
<addon id="script.video.F4mProxy" 
	     name="F4mProxy" 
	     version="2.8.7" 
	     provider-name="Shani">
  <requires>
    <import addon="xbmc.python" version="2.1.0" />
    <import addon="script.module.requests" />
  </requires>
  <extension point="xbmc.python.module" library="lib" />
    <extension point="xbmc.python.pluginsource" library="addon.py">
		<provides>executable</provides>
  </extension>   
  <extension point="xbmc.addon.metadata">
    <platform>all</platform>
    <summary lang="en">Proxy for f4m</summary>
    <description lang="en">Use this addon to play F4m v1 and v2 streams</description>
  </extension>
</addon>
<?xml version="1.0" encoding="UTF-8"?>
<addon id="skin.FTV-mod" version="1.0.6" name="FTV - Wardoctor Mod" provider-name="Wardoctor">
	<requires>
		<import addon="xbmc.gui" version="5.12.0"/>
		<import addon="script.toolbox" version="1.1.1"/>
		<import addon="script.extendedinfo" version="5.6.0"/>
		<import addon="script.globalsearch" version="7.4.4"/>
		<import addon="script.skinshortcuts" version="1.0.13"/>
		<import addon="script.artwork.downloader" version="13.1.0"/>
		<import addon="script.skin.helper.service" version="1.1.1"/>
		<import addon="script.skin.helper.widgets" version="1.0.20"/>
		<import addon="script.skin.helper.skinbackup" version="1.0.12"/>
		<import addon="script.module.autocompletion" version="1.1.2"/>
	</requires>
	<extension point="xbmc.gui.skin" effectslowdown="1.00" debugging="false">
		<res width="1920" height="1080" aspect="16:9" default="true" folder="16x9" />
	</extension>
	<extension point="xbmc.addon.metadata">
		<platform>all</platform>
		<summary lang="en">Skin based on the Fire TV UI</summary>
		<disclaimer lang="en">No mouse or touch support</disclaimer>
		<description lang="en">Fork of Hitcher's fTV skin with nearly full PVR functionality, plus changed a lot of behaviours and added dozens of other features[CR][CR]Skin description: Provides the look and feel of the Fire TV user interface.[CR]For the complete experience enable 'TV Show wide icons' and either use Artwork Downloader to grab logos or create your own artwork and add it to the database (see forum for more details).</description>
		<source>https://github.com/thewardoctor/skin.FTV-mod</source>
		<forum></forum>
		<license>Apache 2.0</license>
		<assets>
            <icon>resources/icon.png</icon>
            <fanart>resources/fanart.jpg</fanart>
            <screenshot>resources/screen1.jpg</screenshot>
            <screenshot>resources/screen2.jpg</screenshot>
            <screenshot>resources/screen3.jpg</screenshot>
            <screenshot>resources/screen4.jpg</screenshot>
            <screenshot>resources/screen5.jpg</screenshot>
        </assets>
		<news>Changelog:
[B]1.0.1[/B]
- Forked</news>
	</extension>
</addon>
</addons> 
